[
    {
        "id": 0,
        "start": 64.50,
        "end": 69.14,
        "text": "ねぇ\n夢喰いバク\nもしもいるのなら"
    },
    {
        "id": 1,
        "start": 69.14,
        "end": 73.14,
        "text": "どうか今夜\nあの子の\n夢を守って"
    },
    {
        "id": 2,
        "start": 73.14,
        "end": 78.14,
        "text": "ささくれみたいな\n後悔のドア\n閉める言葉"
    },
    {
        "id": 3,
        "start": 78.14,
        "end": 88.14,
        "text": "全部\n悪い夢にして\n食べ尽くして"
    },
    {
        "id": 4,
        "start": 91.14,
        "end": 95.14,
        "text": "にぎやかな\n昼休み"
    }
]